LICENSE
MANIFEST.in
README.md
setup.py
pyOxaPayAPI/__init__.py
pyOxaPayAPI/api.py
pyOxaPayAPI/tests.py
pyOxaPayAPI/version.py
pyOxaPayAPI.egg-info/PKG-INFO
pyOxaPayAPI.egg-info/SOURCES.txt
pyOxaPayAPI.egg-info/dependency_links.txt
pyOxaPayAPI.egg-info/top_level.txt