Metadata-Version: 2.4
Name: pyOxaPayAPI
Version: 0.1.0
Summary: Python implementation of OxaPay (https://oxapay.com) pubilc API
Home-page: https://github.com/Badiboy/pyOxaPayAPI
Author: Badiboy
License: MIT license
Keywords: Crypto Pay API OxaPay
Classifier: Development Status :: 3 - Alpha
Classifier: Programming Language :: Python :: 3
Classifier: License :: OSI Approved :: MIT License
Requires: requests
License-File: LICENSE
Dynamic: author
Dynamic: classifier
Dynamic: description
Dynamic: description-content-type
Dynamic: home-page
Dynamic: keywords
Dynamic: license
Dynamic: license-file
Dynamic: requires
Dynamic: summary
